sphinx_jekyll_builder/__init__.py
sphinx_jekyll_builder/jekyll_builder.py
sphinx_jekyll_builder/jekyll_writer.py
sphinx_jekyll_builder-0.3.0.dist-info/LICENSE
sphinx_jekyll_builder-0.3.0.dist-info/METADATA
sphinx_jekyll_builder-0.3.0.dist-info/WHEEL
sphinx_jekyll_builder-0.3.0.dist-info/entry_points.txt
sphinx_jekyll_builder-0.3.0.dist-info/top_level.txt
sphinx_jekyll_builder-0.3.0.dist-info/RECORD
