Metadata-Version: 2.1
Name: sphinx-jekyll-builder
Version: 0.3.0
Summary: sphinx builder that outputs jekyll compatible markdown files with frontmatter
Home-page: https://github.com/codejamninja/sphinx-jekyll-builder
Author: Jam Risser
Author-email: jam@codejam.ninja
License: MIT
Keywords: sphinx docs documentation jekyll
Platform: UNKNOWN
Classifier: Development Status :: 4 - Beta
Classifier: Intended Audience :: Developers
Classifier: Topic :: Utilities
Classifier: License :: OSI Approved :: MIT License
Classifier: Programming Language :: Python :: 2
Classifier: Programming Language :: Python :: 2.7
Classifier: Programming Language :: Python :: 3
Classifier: Programming Language :: Python :: 3.3
Classifier: Programming Language :: Python :: 3.4
Classifier: Programming Language :: Python :: 3.5
Requires-Dist: alabaster (>=0.7.12)
Requires-Dist: Babel (>=2.6.0)
Requires-Dist: certifi (>=2018.11.29)
Requires-Dist: chardet (>=3.0.4)
Requires-Dist: docutils (>=0.14)
Requires-Dist: html2text (>=2018.1.9)
Requires-Dist: idna (>=2.8)
Requires-Dist: imagesize (>=1.1.0)
Requires-Dist: Jinja2 (>=2.10.1)
Requires-Dist: MarkupSafe (>=1.1.0)
Requires-Dist: munch (>=2.3.2)
Requires-Dist: packaging (>=19.0)
Requires-Dist: pydash (>=4.7.4)
Requires-Dist: Pygments (>=2.3.1)
Requires-Dist: pyparsing (>=2.3.1)
Requires-Dist: pytz (>=2018.9)
Requires-Dist: PyYAML (>=5.1)
Requires-Dist: requests (>=2.21.0)
Requires-Dist: six (>=1.12.0)
Requires-Dist: snowballstemmer (>=1.2.1)
Requires-Dist: Sphinx (>=1.8.3)
Requires-Dist: sphinx-markdown-builder (>=0.5.3)
Requires-Dist: sphinxcontrib-websupport (>=1.1.0)
Requires-Dist: typing (>=3.6.6)
Requires-Dist: urllib3 (>=1.24.2)
